hydraters-0.1.2.dist-info/METADATA
hydraters-0.1.2.dist-info/WHEEL
hydraters-0.1.2.dist-info/licenses/LICENSE
hydraters/__init__.py
hydraters/__init__.pyi
hydraters/py.typed
hydraters/hydraters.cpython-310-powerpc64le-linux-gnu.so
hydraters-0.1.2.dist-info/RECORD
