Metadata-Version: 2.4
Name: hydraters
Version: 0.1.2
Classifier: Programming Language :: Rust
Classifier: Programming Language :: Python :: Implementation :: CPython
Classifier: Programming Language :: Python :: Implementation :: PyPy
Classifier: Programming Language :: Python :: 3.9
Classifier: Programming Language :: Python :: 3.10
Classifier: Programming Language :: Python :: 3.11
Classifier: Programming Language :: Python :: 3.12
Classifier: Programming Language :: Python :: 3.13
License-File: LICENSE
Summary: Hydrate Python dictionaries with Rust.
Author-email: David Bitner <bitner@dbspatial.com>, Pete Gadomski <pete.gadomski@gmail.com>
Requires-Python: >=3.9
Project-URL: Repository, https://github.com/developmentseed/hydraters
